[
    {
        "row": 0,
        "col": 2857,
        "value": 1.0
    },
    {
        "row": 3,
        "col": 75,
        "value": 1.0
    },
    {
        "row": 3,
        "col": 509,
        "value": 1.0
    },
    {
        "row": 3,
        "col": 1350,
        "value": 1.0
    },
    {
        "row": 3,
        "col": 2068,
        "value": 1.0
    },
    {
        "row": 4,
        "col": 2003,
        "value": 1.0
    },
    {
        "row": 4,
        "col": 2115,
        "value": 1.0
    },
    {
        "row": 4,
        "col": 2798,
        "value": 1.0
    },
    {
        "row": 4,
        "col": 2943,
        "value": 1.0
    },
    {
        "row": 13,
        "col": 42,
        "value": 1.0
    },
    {
        "row": 13,
        "col": 970,
        "value": 1.0
    },
    {
        "row": 13,
        "col": 1618,
        "value": 1.0
    },
    {
        "row": 13,
        "col": 2680,
        "value": 1.0
    },
    {
        "row": 13,
        "col": 2685,
        "value": 1.0
    },
    {
        "row": 20,
        "col": 1552,
        "value": 1.0
    },
    {
        "row": 20,
        "col": 2423,
        "value": 1.0
    },
    {
        "row": 20,
        "col": 2671,
        "value": 1.0
    },
    {
        "row": 22,
        "col": 88,
        "value": 1.0
    },
    {
        "row": 22,
        "col": 145,
        "value": 1.0
    },
    {
        "row": 22,
        "col": 147,
        "value": 1.0
    },
    {
        "row": 22,
        "col": 253,
        "value": 1.0
    },
    {
        "row": 22,
        "col": 386,
        "value": 2.0
    },
    {
        "row": 22,
        "col": 387,
        "value": 2.0
    },
    {
        "row": 22,
        "col": 407,
        "value": 1.0
    },
    {
        "row": 22,
        "col": 463,
        "value": 2.0
    },
    {
        "row": 22,
        "col": 491,
        "value": 1.0
    },
    {
        "row": 22,
        "col": 543,
        "value": 1.0
    },
    {
        "row": 22,
        "col": 644,
        "value": 1.0
    },
    {
        "row": 22,
        "col": 666,
        "value": 1.0
    },
    {
        "row": 22,
        "col": 767,
        "value": 1.0
    },
    {
        "row": 22,
        "col": 778,
        "value": 1.0
    },
    {
        "row": 22,
        "col": 856,
        "value": 1.0
    },
    {
        "row": 22,
        "col": 970,
        "value": 1.0
    },
    {
        "row": 22,
        "col": 997,
        "value": 1.0
    },
    {
        "row": 22,
        "col": 1067,
        "value": 1.0
    },
    {
        "row": 22,
        "col": 1122,
        "value": 1.0
    },
    {
        "row": 22,
        "col": 1141,
        "value": 1.0
    },
    {
        "row": 22,
        "col": 1263,
        "value": 2.0
    },
    {
        "row": 22,
        "col": 1473,
        "value": 1.0
    },
    {
        "row": 22,
        "col": 1483,
        "value": 1.0
    },
    {
        "row": 22,
        "col": 1486,
        "value": 1.0
    },
    {
        "row": 22,
        "col": 1507,
        "value": 1.0
    },
    {
        "row": 22,
        "col": 1552,
        "value": 3.0
    },
    {
        "row": 22,
        "col": 1699,
        "value": 1.0
    },
    {
        "row": 22,
        "col": 1706,
        "value": 1.0
    },
    {
        "row": 22,
        "col": 1730,
        "value": 1.0
    },
    {
        "row": 22,
        "col": 1817,
        "value": 2.0
    },
    {
        "row": 22,
        "col": 1850,
        "value": 1.0
    },
    {
        "row": 22,
        "col": 1891,
        "value": 2.0
    },
    {
        "row": 22,
        "col": 1989,
        "value": 2.0
    },
    {
        "row": 22,
        "col": 2006,
        "value": 1.0
    },
    {
        "row": 22,
        "col": 2015,
        "value": 1.0
    },
    {
        "row": 22,
        "col": 2243,
        "value": 2.0
    },
    {
        "row": 22,
        "col": 2290,
        "value": 1.0
    },
    {
        "row": 22,
        "col": 2386,
        "value": 1.0
    },
    {
        "row": 22,
        "col": 2423,
        "value": 3.0
    },
    {
        "row": 22,
        "col": 2436,
        "value": 1.0
    },
    {
        "row": 22,
        "col": 2489,
        "value": 1.0
    },
    {
        "row": 22,
        "col": 2537,
        "value": 1.0
    },
    {
        "row": 22,
        "col": 2555,
        "value": 1.0
    },
    {
        "row": 22,
        "col": 2636,
        "value": 1.0
    },
    {
        "row": 22,
        "col": 2671,
        "value": 2.0
    },
    {
        "row": 22,
        "col": 2704,
        "value": 1.0
    },
    {
        "row": 22,
        "col": 2713,
        "value": 1.0
    },
    {
        "row": 22,
        "col": 2883,
        "value": 1.0
    },
    {
        "row": 30,
        "col": 954,
        "value": 1.0
    },
    {
        "row": 30,
        "col": 1262,
        "value": 1.0
    },
    {
        "row": 30,
        "col": 2051,
        "value": 1.0
    },
    {
        "row": 30,
        "col": 2194,
        "value": 1.0
    },
    {
        "row": 35,
        "col": 378,
        "value": 1.0
    },
    {
        "row": 35,
        "col": 600,
        "value": 1.0
    },
    {
        "row": 35,
        "col": 609,
        "value": 1.0
    },
    {
        "row": 35,
        "col": 1094,
        "value": 1.0
    },
    {
        "row": 35,
        "col": 1242,
        "value": 2.0
    },
    {
        "row": 35,
        "col": 1385,
        "value": 1.0
    },
    {
        "row": 35,
        "col": 1817,
        "value": 1.0
    },
    {
        "row": 35,
        "col": 2243,
        "value": 1.0
    },
    {
        "row": 35,
        "col": 2801,
        "value": 1.0
    },
    {
        "row": 45,
        "col": 1087,
        "value": 1.0
    },
    {
        "row": 45,
        "col": 1862,
        "value": 1.0
    },
    {
        "row": 45,
        "col": 2166,
        "value": 1.0
    },
    {
        "row": 45,
        "col": 2743,
        "value": 1.0
    },
    {
        "row": 46,
        "col": 0,
        "value": 1.0
    },
    {
        "row": 48,
        "col": 214,
        "value": 1.0
    },
    {
        "row": 48,
        "col": 277,
        "value": 1.0
    },
    {
        "row": 48,
        "col": 1333,
        "value": 1.0
    },
    {
        "row": 70,
        "col": 75,
        "value": 2.0
    },
    {
        "row": 70,
        "col": 99,
        "value": 1.0
    },
    {
        "row": 70,
        "col": 636,
        "value": 1.0
    },
    {
        "row": 70,
        "col": 738,
        "value": 1.0
    },
    {
        "row": 70,
        "col": 882,
        "value": 1.0
    },
    {
        "row": 70,
        "col": 938,
        "value": 1.0
    },
    {
        "row": 70,
        "col": 1350,
        "value": 1.0
    },
    {
        "row": 70,
        "col": 1807,
        "value": 1.0
    },
    {
        "row": 70,
        "col": 2068,
        "value": 1.0
    },
    {
        "row": 70,
        "col": 2135,
        "value": 1.0
    },
    {
        "row": 70,
        "col": 2427,
        "value": 1.0
    },
    {
        "row": 79,
        "col": 2312,
        "value": 1.0
    },
    {
        "row": 81,
        "col": 145,
        "value": 1.0
    },
    {
        "row": 81,
        "col": 970,
        "value": 1.0
    },
    {
        "row": 81,
        "col": 1507,
        "value": 1.0
    },
    {
        "row": 81,
        "col": 2436,
        "value": 1.0
    },
    {
        "row": 84,
        "col": 281,
        "value": 1.0
    },
    {
        "row": 84,
        "col": 618,
        "value": 3.0
    },
    {
        "row": 84,
        "col": 1247,
        "value": 1.0
    },
    {
        "row": 84,
        "col": 1263,
        "value": 2.0
    },
    {
        "row": 84,
        "col": 1483,
        "value": 1.0
    },
    {
        "row": 84,
        "col": 2290,
        "value": 1.0
    },
    {
        "row": 89,
        "col": 534,
        "value": 1.0
    },
    {
        "row": 89,
        "col": 1649,
        "value": 1.0
    },
    {
        "row": 97,
        "col": 102,
        "value": 1.0
    },
    {
        "row": 97,
        "col": 123,
        "value": 1.0
    },
    {
        "row": 97,
        "col": 1746,
        "value": 1.0
    },
    {
        "row": 97,
        "col": 1903,
        "value": 1.0
    },
    {
        "row": 97,
        "col": 2164,
        "value": 1.0
    },
    {
        "row": 103,
        "col": 50,
        "value": 1.0
    },
    {
        "row": 103,
        "col": 1173,
        "value": 1.0
    },
    {
        "row": 103,
        "col": 1228,
        "value": 1.0
    },
    {
        "row": 103,
        "col": 2068,
        "value": 1.0
    },
    {
        "row": 103,
        "col": 2457,
        "value": 1.0
    },
    {
        "row": 106,
        "col": 233,
        "value": 1.0
    },
    {
        "row": 106,
        "col": 2732,
        "value": 1.0
    },
    {
        "row": 120,
        "col": 387,
        "value": 2.0
    },
    {
        "row": 120,
        "col": 1891,
        "value": 2.0
    },
    {
        "row": 127,
        "col": 482,
        "value": 1.0
    },
    {
        "row": 127,
        "col": 915,
        "value": 1.0
    },
    {
        "row": 127,
        "col": 940,
        "value": 1.0
    },
    {
        "row": 127,
        "col": 1378,
        "value": 1.0
    },
    {
        "row": 127,
        "col": 2482,
        "value": 1.0
    },
    {
        "row": 127,
        "col": 2570,
        "value": 1.0
    },
    {
        "row": 127,
        "col": 2951,
        "value": 1.0
    },
    {
        "row": 140,
        "col": 2026,
        "value": 1.0
    },
    {
        "row": 140,
        "col": 2445,
        "value": 1.0
    },
    {
        "row": 140,
        "col": 2771,
        "value": 1.0
    },
    {
        "row": 143,
        "col": 18,
        "value": 1.0
    },
    {
        "row": 143,
        "col": 716,
        "value": 1.0
    },
    {
        "row": 143,
        "col": 793,
        "value": 1.0
    },
    {
        "row": 143,
        "col": 1620,
        "value": 1.0
    },
    {
        "row": 143,
        "col": 2066,
        "value": 1.0
    },
    {
        "row": 143,
        "col": 2196,
        "value": 1.0
    },
    {
        "row": 143,
        "col": 2350,
        "value": 1.0
    },
    {
        "row": 143,
        "col": 2354,
        "value": 1.0
    },
    {
        "row": 143,
        "col": 2619,
        "value": 1.0
    },
    {
        "row": 143,
        "col": 2656,
        "value": 1.0
    },
    {
        "row": 143,
        "col": 2816,
        "value": 1.0
    },
    {
        "row": 143,
        "col": 2832,
        "value": 1.0
    },
    {
        "row": 143,
        "col": 2922,
        "value": 1.0
    },
    {
        "row": 146,
        "col": 355,
        "value": 1.0
    },
    {
        "row": 146,
        "col": 1385,
        "value": 1.0
    },
    {
        "row": 146,
        "col": 2198,
        "value": 1.0
    },
    {
        "row": 146,
        "col": 2892,
        "value": 1.0
    },
    {
        "row": 150,
        "col": 75,
        "value": 1.0
    },
    {
        "row": 150,
        "col": 355,
        "value": 1.0
    },
    {
        "row": 150,
        "col": 463,
        "value": 1.0
    },
    {
        "row": 150,
        "col": 1385,
        "value": 1.0
    },
    {
        "row": 150,
        "col": 2198,
        "value": 1.0
    },
    {
        "row": 150,
        "col": 2757,
        "value": 1.0
    },
    {
        "row": 150,
        "col": 2758,
        "value": 1.0
    },
    {
        "row": 150,
        "col": 2892,
        "value": 1.0
    },
    {
        "row": 153,
        "col": 0,
        "value": 1.0
    },
    {
        "row": 157,
        "col": 162,
        "value": 1.0
    },
    {
        "row": 157,
        "col": 970,
        "value": 1.0
    },
    {
        "row": 157,
        "col": 2142,
        "value": 1.0
    },
    {
        "row": 157,
        "col": 2554,
        "value": 1.0
    },
    {
        "row": 157,
        "col": 2754,
        "value": 1.0
    },
    {
        "row": 157,
        "col": 2903,
        "value": 1.0
    },
    {
        "row": 161,
        "col": 946,
        "value": 1.0
    },
    {
        "row": 166,
        "col": 26,
        "value": 1.0
    },
    {
        "row": 166,
        "col": 37,
        "value": 1.0
    },
    {
        "row": 166,
        "col": 57,
        "value": 1.0
    },
    {
        "row": 166,
        "col": 108,
        "value": 1.0
    },
    {
        "row": 166,
        "col": 145,
        "value": 1.0
    },
    {
        "row": 166,
        "col": 276,
        "value": 1.0
    },
    {
        "row": 166,
        "col": 283,
        "value": 1.0
    },
    {
        "row": 166,
        "col": 387,
        "value": 3.0
    },
    {
        "row": 166,
        "col": 453,
        "value": 2.0
    },
    {
        "row": 166,
        "col": 512,
        "value": 1.0
    },
    {
        "row": 166,
        "col": 534,
        "value": 3.0
    },
    {
        "row": 166,
        "col": 544,
        "value": 1.0
    },
    {
        "row": 166,
        "col": 552,
        "value": 1.0
    },
    {
        "row": 166,
        "col": 574,
        "value": 1.0
    },
    {
        "row": 166,
        "col": 608,
        "value": 1.0
    },
    {
        "row": 166,
        "col": 680,
        "value": 1.0
    },
    {
        "row": 166,
        "col": 683,
        "value": 1.0
    },
    {
        "row": 166,
        "col": 686,
        "value": 2.0
    },
    {
        "row": 166,
        "col": 710,
        "value": 1.0
    },
    {
        "row": 166,
        "col": 720,
        "value": 1.0
    },
    {
        "row": 166,
        "col": 736,
        "value": 1.0
    },
    {
        "row": 166,
        "col": 757,
        "value": 1.0
    },
    {
        "row": 166,
        "col": 842,
        "value": 1.0
    },
    {
        "row": 166,
        "col": 865,
        "value": 1.0
    },
    {
        "row": 166,
        "col": 876,
        "value": 1.0
    },
    {
        "row": 166,
        "col": 894,
        "value": 1.0
    },
    {
        "row": 166,
        "col": 913,
        "value": 1.0
    },
    {
        "row": 166,
        "col": 970,
        "value": 2.0
    },
    {
        "row": 166,
        "col": 1009,
        "value": 3.0
    },
    {
        "row": 166,
        "col": 1058,
        "value": 1.0
    },
    {
        "row": 166,
        "col": 1102,
        "value": 1.0
    },
    {
        "row": 166,
        "col": 1127,
        "value": 2.0
    },
    {
        "row": 166,
        "col": 1132,
        "value": 1.0
    },
    {
        "row": 166,
        "col": 1156,
        "value": 1.0
    },
    {
        "row": 166,
        "col": 1168,
        "value": 1.0
    },
    {
        "row": 166,
        "col": 1186,
        "value": 1.0
    },
    {
        "row": 166,
        "col": 1250,
        "value": 1.0
    },
    {
        "row": 166,
        "col": 1252,
        "value": 1.0
    },
    {
        "row": 166,
        "col": 1257,
        "value": 1.0
    },
    {
        "row": 166,
        "col": 1280,
        "value": 1.0
    },
    {
        "row": 166,
        "col": 1304,
        "value": 1.0
    },
    {
        "row": 166,
        "col": 1359,
        "value": 1.0
    },
    {
        "row": 166,
        "col": 1368,
        "value": 1.0
    },
    {
        "row": 166,
        "col": 1392,
        "value": 4.0
    },
    {
        "row": 166,
        "col": 1424,
        "value": 1.0
    },
    {
        "row": 166,
        "col": 1442,
        "value": 6.0
    },
    {
        "row": 166,
        "col": 1479,
        "value": 1.0
    },
    {
        "row": 166,
        "col": 1504,
        "value": 1.0
    },
    {
        "row": 166,
        "col": 1508,
        "value": 1.0
    },
    {
        "row": 166,
        "col": 1518,
        "value": 1.0
    },
    {
        "row": 166,
        "col": 1519,
        "value": 1.0
    },
    {
        "row": 166,
        "col": 1552,
        "value": 1.0
    },
    {
        "row": 166,
        "col": 1553,
        "value": 1.0
    },
    {
        "row": 166,
        "col": 1649,
        "value": 3.0
    },
    {
        "row": 166,
        "col": 1666,
        "value": 1.0
    },
    {
        "row": 166,
        "col": 1708,
        "value": 1.0
    },
    {
        "row": 166,
        "col": 1745,
        "value": 1.0
    },
    {
        "row": 166,
        "col": 1760,
        "value": 1.0
    },
    {
        "row": 166,
        "col": 1765,
        "value": 1.0
    },
    {
        "row": 166,
        "col": 1798,
        "value": 1.0
    },
    {
        "row": 166,
        "col": 1845,
        "value": 1.0
    },
    {
        "row": 166,
        "col": 1891,
        "value": 3.0
    },
    {
        "row": 166,
        "col": 1953,
        "value": 4.0
    },
    {
        "row": 166,
        "col": 2024,
        "value": 1.0
    },
    {
        "row": 166,
        "col": 2026,
        "value": 2.0
    },
    {
        "row": 166,
        "col": 2041,
        "value": 1.0
    },
    {
        "row": 166,
        "col": 2107,
        "value": 1.0
    },
    {
        "row": 166,
        "col": 2139,
        "value": 3.0
    },
    {
        "row": 166,
        "col": 2142,
        "value": 1.0
    },
    {
        "row": 166,
        "col": 2150,
        "value": 1.0
    },
    {
        "row": 166,
        "col": 2198,
        "value": 1.0
    },
    {
        "row": 166,
        "col": 2205,
        "value": 1.0
    },
    {
        "row": 166,
        "col": 2262,
        "value": 2.0
    },
    {
        "row": 166,
        "col": 2281,
        "value": 1.0
    },
    {
        "row": 166,
        "col": 2283,
        "value": 1.0
    },
    {
        "row": 166,
        "col": 2287,
        "value": 1.0
    },
    {
        "row": 166,
        "col": 2290,
        "value": 1.0
    },
    {
        "row": 166,
        "col": 2300,
        "value": 1.0
    },
    {
        "row": 166,
        "col": 2326,
        "value": 1.0
    },
    {
        "row": 166,
        "col": 2356,
        "value": 2.0
    },
    {
        "row": 166,
        "col": 2375,
        "value": 1.0
    },
    {
        "row": 166,
        "col": 2409,
        "value": 1.0
    },
    {
        "row": 166,
        "col": 2423,
        "value": 1.0
    },
    {
        "row": 166,
        "col": 2445,
        "value": 1.0
    },
    {
        "row": 166,
        "col": 2478,
        "value": 1.0
    },
    {
        "row": 166,
        "col": 2485,
        "value": 1.0
    },
    {
        "row": 166,
        "col": 2503,
        "value": 1.0
    },
    {
        "row": 166,
        "col": 2529,
        "value": 1.0
    },
    {
        "row": 166,
        "col": 2547,
        "value": 1.0
    },
    {
        "row": 166,
        "col": 2636,
        "value": 1.0
    },
    {
        "row": 166,
        "col": 2702,
        "value": 1.0
    },
    {
        "row": 166,
        "col": 2710,
        "value": 1.0
    },
    {
        "row": 166,
        "col": 2771,
        "value": 1.0
    },
    {
        "row": 166,
        "col": 2790,
        "value": 1.0
    },
    {
        "row": 166,
        "col": 2853,
        "value": 1.0
    },
    {
        "row": 166,
        "col": 2879,
        "value": 2.0
    },
    {
        "row": 166,
        "col": 2888,
        "value": 1.0
    },
    {
        "row": 166,
        "col": 2892,
        "value": 12.0
    },
    {
        "row": 166,
        "col": 2929,
        "value": 1.0
    },
    {
        "row": 167,
        "col": 299,
        "value": 1.0
    },
    {
        "row": 169,
        "col": 534,
        "value": 1.0
    },
    {
        "row": 169,
        "col": 2290,
        "value": 1.0
    },
    {
        "row": 169,
        "col": 2485,
        "value": 1.0
    },
    {
        "row": 169,
        "col": 2636,
        "value": 1.0
    },
    {
        "row": 175,
        "col": 2290,
        "value": 1.0
    },
    {
        "row": 176,
        "col": 1557,
        "value": 1.0
    },
    {
        "row": 177,
        "col": 99,
        "value": 1.0
    },
    {
        "row": 177,
        "col": 2004,
        "value": 1.0
    },
    {
        "row": 188,
        "col": 387,
        "value": 1.0
    },
    {
        "row": 188,
        "col": 702,
        "value": 1.0
    },
    {
        "row": 188,
        "col": 1500,
        "value": 1.0
    },
    {
        "row": 188,
        "col": 1674,
        "value": 1.0
    },
    {
        "row": 188,
        "col": 1891,
        "value": 1.0
    },
    {
        "row": 193,
        "col": 1263,
        "value": 1.0
    },
    {
        "row": 193,
        "col": 2269,
        "value": 1.0
    },
    {
        "row": 193,
        "col": 2676,
        "value": 2.0
    },
    {
        "row": 196,
        "col": 6,
        "value": 1.0
    },
    {
        "row": 196,
        "col": 18,
        "value": 2.0
    },
    {
        "row": 196,
        "col": 52,
        "value": 1.0
    },
    {
        "row": 196,
        "col": 246,
        "value": 1.0
    },
    {
        "row": 196,
        "col": 252,
        "value": 1.0
    },
    {
        "row": 196,
        "col": 272,
        "value": 1.0
    },
    {
        "row": 196,
        "col": 278,
        "value": 1.0
    },
    {
        "row": 196,
        "col": 281,
        "value": 3.0
    },
    {
        "row": 196,
        "col": 290,
        "value": 1.0
    },
    {
        "row": 196,
        "col": 291,
        "value": 1.0
    },
    {
        "row": 196,
        "col": 295,
        "value": 1.0
    },
    {
        "row": 196,
        "col": 304,
        "value": 1.0
    },
    {
        "row": 196,
        "col": 309,
        "value": 1.0
    },
    {
        "row": 196,
        "col": 322,
        "value": 1.0
    },
    {
        "row": 196,
        "col": 335,
        "value": 1.0
    },
    {
        "row": 196,
        "col": 387,
        "value": 2.0
    },
    {
        "row": 196,
        "col": 397,
        "value": 1.0
    },
    {
        "row": 196,
        "col": 407,
        "value": 1.0
    },
    {
        "row": 196,
        "col": 427,
        "value": 1.0
    },
    {
        "row": 196,
        "col": 513,
        "value": 1.0
    },
    {
        "row": 196,
        "col": 552,
        "value": 1.0
    },
    {
        "row": 196,
        "col": 573,
        "value": 1.0
    },
    {
        "row": 196,
        "col": 618,
        "value": 6.0
    },
    {
        "row": 196,
        "col": 646,
        "value": 1.0
    },
    {
        "row": 196,
        "col": 653,
        "value": 1.0
    },
    {
        "row": 196,
        "col": 654,
        "value": 1.0
    },
    {
        "row": 196,
        "col": 661,
        "value": 1.0
    },
    {
        "row": 196,
        "col": 696,
        "value": 1.0
    },
    {
        "row": 196,
        "col": 697,
        "value": 1.0
    },
    {
        "row": 196,
        "col": 748,
        "value": 1.0
    },
    {
        "row": 196,
        "col": 781,
        "value": 2.0
    },
    {
        "row": 196,
        "col": 854,
        "value": 1.0
    },
    {
        "row": 196,
        "col": 859,
        "value": 1.0
    },
    {
        "row": 196,
        "col": 867,
        "value": 1.0
    },
    {
        "row": 196,
        "col": 893,
        "value": 1.0
    },
    {
        "row": 196,
        "col": 895,
        "value": 1.0
    },
    {
        "row": 196,
        "col": 924,
        "value": 1.0
    },
    {
        "row": 196,
        "col": 932,
        "value": 1.0
    },
    {
        "row": 196,
        "col": 950,
        "value": 1.0
    },
    {
        "row": 196,
        "col": 957,
        "value": 1.0
    },
    {
        "row": 196,
        "col": 970,
        "value": 1.0
    },
    {
        "row": 196,
        "col": 989,
        "value": 1.0
    },
    {
        "row": 196,
        "col": 997,
        "value": 1.0
    },
    {
        "row": 196,
        "col": 1005,
        "value": 1.0
    },
    {
        "row": 196,
        "col": 1009,
        "value": 1.0
    },
    {
        "row": 196,
        "col": 1032,
        "value": 1.0
    },
    {
        "row": 196,
        "col": 1054,
        "value": 2.0
    },
    {
        "row": 196,
        "col": 1070,
        "value": 2.0
    },
    {
        "row": 196,
        "col": 1076,
        "value": 1.0
    },
    {
        "row": 196,
        "col": 1087,
        "value": 4.0
    },
    {
        "row": 196,
        "col": 1107,
        "value": 1.0
    },
    {
        "row": 196,
        "col": 1119,
        "value": 1.0
    },
    {
        "row": 196,
        "col": 1122,
        "value": 1.0
    },
    {
        "row": 196,
        "col": 1135,
        "value": 1.0
    },
    {
        "row": 196,
        "col": 1144,
        "value": 1.0
    },
    {
        "row": 196,
        "col": 1188,
        "value": 2.0
    },
    {
        "row": 196,
        "col": 1247,
        "value": 3.0
    },
    {
        "row": 196,
        "col": 1263,
        "value": 2.0
    },
    {
        "row": 196,
        "col": 1284,
        "value": 1.0
    },
    {
        "row": 196,
        "col": 1292,
        "value": 1.0
    },
    {
        "row": 196,
        "col": 1336,
        "value": 1.0
    },
    {
        "row": 196,
        "col": 1341,
        "value": 1.0
    },
    {
        "row": 196,
        "col": 1342,
        "value": 1.0
    },
    {
        "row": 196,
        "col": 1351,
        "value": 1.0
    },
    {
        "row": 196,
        "col": 1353,
        "value": 1.0
    },
    {
        "row": 196,
        "col": 1359,
        "value": 1.0
    },
    {
        "row": 196,
        "col": 1367,
        "value": 1.0
    },
    {
        "row": 196,
        "col": 1389,
        "value": 1.0
    },
    {
        "row": 196,
        "col": 1483,
        "value": 2.0
    },
    {
        "row": 196,
        "col": 1525,
        "value": 1.0
    },
    {
        "row": 196,
        "col": 1583,
        "value": 1.0
    },
    {
        "row": 196,
        "col": 1593,
        "value": 1.0
    },
    {
        "row": 196,
        "col": 1639,
        "value": 1.0
    },
    {
        "row": 196,
        "col": 1640,
        "value": 1.0
    },
    {
        "row": 196,
        "col": 1651,
        "value": 1.0
    },
    {
        "row": 196,
        "col": 1652,
        "value": 1.0
    },
    {
        "row": 196,
        "col": 1683,
        "value": 1.0
    },
    {
        "row": 196,
        "col": 1687,
        "value": 1.0
    },
    {
        "row": 196,
        "col": 1693,
        "value": 1.0
    },
    {
        "row": 196,
        "col": 1714,
        "value": 1.0
    },
    {
        "row": 196,
        "col": 1731,
        "value": 1.0
    },
    {
        "row": 196,
        "col": 1742,
        "value": 1.0
    },
    {
        "row": 196,
        "col": 1766,
        "value": 1.0
    },
    {
        "row": 196,
        "col": 1798,
        "value": 1.0
    },
    {
        "row": 196,
        "col": 1817,
        "value": 1.0
    },
    {
        "row": 196,
        "col": 1823,
        "value": 1.0
    },
    {
        "row": 196,
        "col": 1865,
        "value": 1.0
    },
    {
        "row": 196,
        "col": 1891,
        "value": 2.0
    },
    {
        "row": 196,
        "col": 1925,
        "value": 1.0
    },
    {
        "row": 196,
        "col": 1981,
        "value": 1.0
    },
    {
        "row": 196,
        "col": 1989,
        "value": 1.0
    },
    {
        "row": 196,
        "col": 1995,
        "value": 1.0
    },
    {
        "row": 196,
        "col": 2006,
        "value": 1.0
    },
    {
        "row": 196,
        "col": 2052,
        "value": 1.0
    },
    {
        "row": 196,
        "col": 2069,
        "value": 1.0
    },
    {
        "row": 196,
        "col": 2145,
        "value": 1.0
    },
    {
        "row": 196,
        "col": 2158,
        "value": 1.0
    },
    {
        "row": 196,
        "col": 2160,
        "value": 1.0
    },
    {
        "row": 196,
        "col": 2171,
        "value": 1.0
    },
    {
        "row": 196,
        "col": 2200,
        "value": 1.0
    },
    {
        "row": 196,
        "col": 2243,
        "value": 1.0
    },
    {
        "row": 196,
        "col": 2244,
        "value": 1.0
    },
    {
        "row": 196,
        "col": 2262,
        "value": 1.0
    },
    {
        "row": 196,
        "col": 2264,
        "value": 1.0
    },
    {
        "row": 196,
        "col": 2270,
        "value": 2.0
    },
    {
        "row": 196,
        "col": 2290,
        "value": 7.0
    },
    {
        "row": 196,
        "col": 2312,
        "value": 2.0
    },
    {
        "row": 196,
        "col": 2376,
        "value": 1.0
    },
    {
        "row": 196,
        "col": 2504,
        "value": 1.0
    },
    {
        "row": 196,
        "col": 2514,
        "value": 1.0
    },
    {
        "row": 196,
        "col": 2554,
        "value": 1.0
    },
    {
        "row": 196,
        "col": 2579,
        "value": 1.0
    },
    {
        "row": 196,
        "col": 2775,
        "value": 1.0
    },
    {
        "row": 196,
        "col": 2793,
        "value": 1.0
    },
    {
        "row": 196,
        "col": 2816,
        "value": 2.0
    },
    {
        "row": 196,
        "col": 2839,
        "value": 1.0
    },
    {
        "row": 196,
        "col": 2859,
        "value": 1.0
    },
    {
        "row": 196,
        "col": 2878,
        "value": 1.0
    },
    {
        "row": 196,
        "col": 2884,
        "value": 1.0
    },
    {
        "row": 196,
        "col": 2892,
        "value": 1.0
    },
    {
        "row": 196,
        "col": 2894,
        "value": 1.0
    },
    {
        "row": 196,
        "col": 2933,
        "value": 1.0
    },
    {
        "row": 197,
        "col": 290,
        "value": 2.0
    },
    {
        "row": 197,
        "col": 2920,
        "value": 2.0
    },
    {
        "row": 210,
        "col": 386,
        "value": 1.0
    },
    {
        "row": 210,
        "col": 387,
        "value": 2.0
    },
    {
        "row": 210,
        "col": 416,
        "value": 1.0
    },
    {
        "row": 210,
        "col": 1076,
        "value": 1.0
    },
    {
        "row": 210,
        "col": 1416,
        "value": 1.0
    },
    {
        "row": 210,
        "col": 1507,
        "value": 1.0
    },
    {
        "row": 210,
        "col": 1604,
        "value": 1.0
    },
    {
        "row": 210,
        "col": 1696,
        "value": 1.0
    },
    {
        "row": 210,
        "col": 1761,
        "value": 1.0
    },
    {
        "row": 210,
        "col": 1798,
        "value": 1.0
    },
    {
        "row": 210,
        "col": 1820,
        "value": 1.0
    },
    {
        "row": 210,
        "col": 1891,
        "value": 2.0
    },
    {
        "row": 210,
        "col": 2436,
        "value": 1.0
    },
    {
        "row": 210,
        "col": 2554,
        "value": 1.0
    },
    {
        "row": 210,
        "col": 2945,
        "value": 1.0
    },
    {
        "row": 211,
        "col": 2312,
        "value": 1.0
    },
    {
        "row": 223,
        "col": 18,
        "value": 1.0
    },
    {
        "row": 223,
        "col": 653,
        "value": 1.0
    },
    {
        "row": 223,
        "col": 957,
        "value": 1.0
    },
    {
        "row": 223,
        "col": 2145,
        "value": 1.0
    },
    {
        "row": 223,
        "col": 2158,
        "value": 1.0
    },
    {
        "row": 223,
        "col": 2244,
        "value": 1.0
    },
    {
        "row": 223,
        "col": 2816,
        "value": 1.0
    },
    {
        "row": 228,
        "col": 371,
        "value": 1.0
    },
    {
        "row": 230,
        "col": 290,
        "value": 2.0
    },
    {
        "row": 230,
        "col": 2920,
        "value": 2.0
    },
    {
        "row": 231,
        "col": 946,
        "value": 1.0
    },
    {
        "row": 248,
        "col": 2857,
        "value": 1.0
    },
    {
        "row": 267,
        "col": 544,
        "value": 1.0
    },
    {
        "row": 267,
        "col": 970,
        "value": 1.0
    },
    {
        "row": 267,
        "col": 2356,
        "value": 1.0
    },
    {
        "row": 267,
        "col": 2409,
        "value": 1.0
    },
    {
        "row": 267,
        "col": 2478,
        "value": 1.0
    },
    {
        "row": 268,
        "col": 2290,
        "value": 1.0
    },
    {
        "row": 268,
        "col": 2636,
        "value": 1.0
    },
    {
        "row": 270,
        "col": 281,
        "value": 1.0
    },
    {
        "row": 270,
        "col": 618,
        "value": 1.0
    },
    {
        "row": 284,
        "col": 648,
        "value": 1.0
    },
    {
        "row": 289,
        "col": 1250,
        "value": 1.0
    },
    {
        "row": 289,
        "col": 1392,
        "value": 3.0
    },
    {
        "row": 289,
        "col": 1442,
        "value": 3.0
    },
    {
        "row": 289,
        "col": 1649,
        "value": 1.0
    },
    {
        "row": 289,
        "col": 1666,
        "value": 1.0
    },
    {
        "row": 289,
        "col": 1953,
        "value": 3.0
    },
    {
        "row": 289,
        "col": 2892,
        "value": 3.0
    },
    {
        "row": 292,
        "col": 997,
        "value": 1.0
    },
    {
        "row": 292,
        "col": 1817,
        "value": 1.0
    },
    {
        "row": 292,
        "col": 1989,
        "value": 1.0
    },
    {
        "row": 292,
        "col": 2243,
        "value": 1.0
    },
    {
        "row": 295,
        "col": 290,
        "value": 2.0
    },
    {
        "row": 295,
        "col": 946,
        "value": 1.0
    },
    {
        "row": 295,
        "col": 2920,
        "value": 2.0
    },
    {
        "row": 296,
        "col": 83,
        "value": 1.0
    },
    {
        "row": 296,
        "col": 157,
        "value": 1.0
    },
    {
        "row": 296,
        "col": 601,
        "value": 1.0
    },
    {
        "row": 296,
        "col": 816,
        "value": 1.0
    },
    {
        "row": 296,
        "col": 970,
        "value": 1.0
    },
    {
        "row": 296,
        "col": 1167,
        "value": 1.0
    },
    {
        "row": 296,
        "col": 2525,
        "value": 1.0
    },
    {
        "row": 298,
        "col": 83,
        "value": 1.0
    },
    {
        "row": 298,
        "col": 157,
        "value": 1.0
    },
    {
        "row": 298,
        "col": 601,
        "value": 1.0
    },
    {
        "row": 298,
        "col": 816,
        "value": 1.0
    },
    {
        "row": 298,
        "col": 970,
        "value": 1.0
    },
    {
        "row": 298,
        "col": 1167,
        "value": 1.0
    },
    {
        "row": 298,
        "col": 2525,
        "value": 1.0
    },
    {
        "row": 303,
        "col": 1822,
        "value": 1.0
    },
    {
        "row": 303,
        "col": 1938,
        "value": 1.0
    },
    {
        "row": 305,
        "col": 75,
        "value": 1.0
    },
    {
        "row": 305,
        "col": 2427,
        "value": 1.0
    },
    {
        "row": 309,
        "col": 867,
        "value": 1.0
    },
    {
        "row": 309,
        "col": 924,
        "value": 1.0
    },
    {
        "row": 309,
        "col": 2015,
        "value": 1.0
    },
    {
        "row": 309,
        "col": 2489,
        "value": 1.0
    },
    {
        "row": 312,
        "col": 502,
        "value": 1.0
    },
    {
        "row": 312,
        "col": 970,
        "value": 1.0
    },
    {
        "row": 312,
        "col": 1076,
        "value": 1.0
    },
    {
        "row": 312,
        "col": 2741,
        "value": 1.0
    },
    {
        "row": 316,
        "col": 1058,
        "value": 1.0
    },
    {
        "row": 316,
        "col": 1156,
        "value": 1.0
    },
    {
        "row": 316,
        "col": 1257,
        "value": 1.0
    },
    {
        "row": 316,
        "col": 2702,
        "value": 1.0
    },
    {
        "row": 319,
        "col": 83,
        "value": 1.0
    },
    {
        "row": 319,
        "col": 816,
        "value": 1.0
    },
    {
        "row": 319,
        "col": 970,
        "value": 1.0
    },
    {
        "row": 319,
        "col": 1079,
        "value": 1.0
    },
    {
        "row": 319,
        "col": 1180,
        "value": 1.0
    },
    {
        "row": 324,
        "col": 1424,
        "value": 1.0
    },
    {
        "row": 324,
        "col": 2026,
        "value": 2.0
    },
    {
        "row": 324,
        "col": 2287,
        "value": 1.0
    },
    {
        "row": 325,
        "col": 162,
        "value": 1.0
    },
    {
        "row": 325,
        "col": 1076,
        "value": 1.0
    },
    {
        "row": 325,
        "col": 1761,
        "value": 1.0
    },
    {
        "row": 325,
        "col": 1798,
        "value": 1.0
    },
    {
        "row": 325,
        "col": 2312,
        "value": 1.0
    },
    {
        "row": 325,
        "col": 2554,
        "value": 1.0
    },
    {
        "row": 325,
        "col": 2642,
        "value": 1.0
    },
    {
        "row": 332,
        "col": 100,
        "value": 2.0
    },
    {
        "row": 332,
        "col": 478,
        "value": 2.0
    },
    {
        "row": 332,
        "col": 482,
        "value": 1.0
    },
    {
        "row": 332,
        "col": 756,
        "value": 1.0
    },
    {
        "row": 332,
        "col": 915,
        "value": 1.0
    },
    {
        "row": 332,
        "col": 940,
        "value": 3.0
    },
    {
        "row": 332,
        "col": 975,
        "value": 2.0
    },
    {
        "row": 332,
        "col": 1099,
        "value": 1.0
    },
    {
        "row": 332,
        "col": 1378,
        "value": 2.0
    },
    {
        "row": 332,
        "col": 2040,
        "value": 2.0
    },
    {
        "row": 332,
        "col": 2482,
        "value": 3.0
    },
    {
        "row": 332,
        "col": 2539,
        "value": 2.0
    },
    {
        "row": 332,
        "col": 2570,
        "value": 2.0
    },
    {
        "row": 332,
        "col": 2620,
        "value": 1.0
    },
    {
        "row": 332,
        "col": 2799,
        "value": 1.0
    },
    {
        "row": 332,
        "col": 2881,
        "value": 1.0
    },
    {
        "row": 332,
        "col": 2951,
        "value": 1.0
    },
    {
        "row": 336,
        "col": 293,
        "value": 1.0
    },
    {
        "row": 336,
        "col": 306,
        "value": 1.0
    },
    {
        "row": 336,
        "col": 1058,
        "value": 1.0
    },
    {
        "row": 336,
        "col": 1156,
        "value": 1.0
    },
    {
        "row": 336,
        "col": 1257,
        "value": 1.0
    },
    {
        "row": 336,
        "col": 1512,
        "value": 1.0
    },
    {
        "row": 336,
        "col": 2113,
        "value": 2.0
    },
    {
        "row": 336,
        "col": 2345,
        "value": 1.0
    },
    {
        "row": 336,
        "col": 2677,
        "value": 2.0
    },
    {
        "row": 336,
        "col": 2702,
        "value": 1.0
    },
    {
        "row": 336,
        "col": 2734,
        "value": 1.0
    },
    {
        "row": 339,
        "col": 1087,
        "value": 1.0
    },
    {
        "row": 339,
        "col": 1862,
        "value": 1.0
    },
    {
        "row": 339,
        "col": 2166,
        "value": 1.0
    },
    {
        "row": 339,
        "col": 2743,
        "value": 1.0
    },
    {
        "row": 340,
        "col": 18,
        "value": 1.0
    },
    {
        "row": 340,
        "col": 893,
        "value": 1.0
    },
    {
        "row": 340,
        "col": 1341,
        "value": 1.0
    },
    {
        "row": 340,
        "col": 2579,
        "value": 1.0
    },
    {
        "row": 340,
        "col": 2816,
        "value": 1.0
    },
    {
        "row": 340,
        "col": 2859,
        "value": 1.0
    },
    {
        "row": 343,
        "col": 50,
        "value": 1.0
    },
    {
        "row": 343,
        "col": 1173,
        "value": 1.0
    },
    {
        "row": 343,
        "col": 1228,
        "value": 1.0
    },
    {
        "row": 343,
        "col": 2068,
        "value": 1.0
    },
    {
        "row": 343,
        "col": 2457,
        "value": 1.0
    },
    {
        "row": 349,
        "col": 534,
        "value": 1.0
    },
    {
        "row": 349,
        "col": 1649,
        "value": 1.0
    },
    {
        "row": 352,
        "col": 387,
        "value": 1.0
    },
    {
        "row": 352,
        "col": 1891,
        "value": 1.0
    },
    {
        "row": 366,
        "col": 834,
        "value": 1.0
    },
    {
        "row": 366,
        "col": 979,
        "value": 1.0
    },
    {
        "row": 366,
        "col": 997,
        "value": 1.0
    },
    {
        "row": 366,
        "col": 1063,
        "value": 1.0
    },
    {
        "row": 366,
        "col": 1074,
        "value": 1.0
    },
    {
        "row": 366,
        "col": 1466,
        "value": 1.0
    },
    {
        "row": 366,
        "col": 1664,
        "value": 1.0
    },
    {
        "row": 366,
        "col": 1989,
        "value": 1.0
    },
    {
        "row": 366,
        "col": 2896,
        "value": 1.0
    },
    {
        "row": 368,
        "col": 1263,
        "value": 1.0
    },
    {
        "row": 368,
        "col": 1483,
        "value": 1.0
    },
    {
        "row": 372,
        "col": 281,
        "value": 1.0
    },
    {
        "row": 372,
        "col": 618,
        "value": 1.0
    },
    {
        "row": 372,
        "col": 1144,
        "value": 1.0
    },
    {
        "row": 372,
        "col": 1351,
        "value": 1.0
    },
    {
        "row": 372,
        "col": 1483,
        "value": 1.0
    },
    {
        "row": 372,
        "col": 1683,
        "value": 1.0
    },
    {
        "row": 372,
        "col": 2445,
        "value": 1.0
    },
    {
        "row": 372,
        "col": 2771,
        "value": 1.0
    },
    {
        "row": 390,
        "col": 2,
        "value": 1.0
    },
    {
        "row": 390,
        "col": 9,
        "value": 1.0
    },
    {
        "row": 390,
        "col": 18,
        "value": 3.0
    },
    {
        "row": 390,
        "col": 83,
        "value": 1.0
    },
    {
        "row": 390,
        "col": 88,
        "value": 1.0
    },
    {
        "row": 390,
        "col": 89,
        "value": 1.0
    },
    {
        "row": 390,
        "col": 96,
        "value": 1.0
    },
    {
        "row": 390,
        "col": 107,
        "value": 1.0
    },
    {
        "row": 390,
        "col": 116,
        "value": 1.0
    },
    {
        "row": 390,
        "col": 128,
        "value": 1.0
    },
    {
        "row": 390,
        "col": 145,
        "value": 2.0
    },
    {
        "row": 390,
        "col": 156,
        "value": 2.0
    },
    {
        "row": 390,
        "col": 160,
        "value": 2.0
    },
    {
        "row": 390,
        "col": 162,
        "value": 2.0
    },
    {
        "row": 390,
        "col": 174,
        "value": 1.0
    },
    {
        "row": 390,
        "col": 246,
        "value": 2.0
    },
    {
        "row": 390,
        "col": 247,
        "value": 1.0
    },
    {
        "row": 390,
        "col": 281,
        "value": 3.0
    },
    {
        "row": 390,
        "col": 300,
        "value": 2.0
    },
    {
        "row": 390,
        "col": 360,
        "value": 7.0
    },
    {
        "row": 390,
        "col": 370,
        "value": 1.0
    },
    {
        "row": 390,
        "col": 371,
        "value": 1.0
    },
    {
        "row": 390,
        "col": 386,
        "value": 2.0
    },
    {
        "row": 390,
        "col": 414,
        "value": 1.0
    },
    {
        "row": 390,
        "col": 442,
        "value": 1.0
    },
    {
        "row": 390,
        "col": 463,
        "value": 8.0
    },
    {
        "row": 390,
        "col": 534,
        "value": 1.0
    },
    {
        "row": 390,
        "col": 539,
        "value": 1.0
    },
    {
        "row": 390,
        "col": 556,
        "value": 1.0
    },
    {
        "row": 390,
        "col": 583,
        "value": 1.0
    },
    {
        "row": 390,
        "col": 586,
        "value": 1.0
    },
    {
        "row": 390,
        "col": 628,
        "value": 1.0
    },
    {
        "row": 390,
        "col": 684,
        "value": 1.0
    },
    {
        "row": 390,
        "col": 716,
        "value": 1.0
    },
    {
        "row": 390,
        "col": 792,
        "value": 1.0
    },
    {
        "row": 390,
        "col": 793,
        "value": 3.0
    },
    {
        "row": 390,
        "col": 796,
        "value": 1.0
    },
    {
        "row": 390,
        "col": 821,
        "value": 1.0
    },
    {
        "row": 390,
        "col": 824,
        "value": 1.0
    },
    {
        "row": 390,
        "col": 829,
        "value": 1.0
    },
    {
        "row": 390,
        "col": 876,
        "value": 1.0
    },
    {
        "row": 390,
        "col": 938,
        "value": 1.0
    },
    {
        "row": 390,
        "col": 948,
        "value": 1.0
    },
    {
        "row": 390,
        "col": 957,
        "value": 1.0
    },
    {
        "row": 390,
        "col": 970,
        "value": 12.0
    },
    {
        "row": 390,
        "col": 1006,
        "value": 1.0
    },
    {
        "row": 390,
        "col": 1011,
        "value": 1.0
    },
    {
        "row": 390,
        "col": 1021,
        "value": 1.0
    },
    {
        "row": 390,
        "col": 1054,
        "value": 1.0
    },
    {
        "row": 390,
        "col": 1076,
        "value": 6.0
    },
    {
        "row": 390,
        "col": 1087,
        "value": 2.0
    },
    {
        "row": 390,
        "col": 1100,
        "value": 1.0
    },
    {
        "row": 390,
        "col": 1180,
        "value": 1.0
    },
    {
        "row": 390,
        "col": 1188,
        "value": 1.0
    },
    {
        "row": 390,
        "col": 1226,
        "value": 1.0
    },
    {
        "row": 390,
        "col": 1263,
        "value": 1.0
    },
    {
        "row": 390,
        "col": 1282,
        "value": 1.0
    },
    {
        "row": 390,
        "col": 1285,
        "value": 1.0
    },
    {
        "row": 390,
        "col": 1292,
        "value": 2.0
    },
    {
        "row": 390,
        "col": 1307,
        "value": 1.0
    },
    {
        "row": 390,
        "col": 1351,
        "value": 1.0
    },
    {
        "row": 390,
        "col": 1406,
        "value": 1.0
    },
    {
        "row": 390,
        "col": 1415,
        "value": 1.0
    },
    {
        "row": 390,
        "col": 1424,
        "value": 1.0
    },
    {
        "row": 390,
        "col": 1483,
        "value": 2.0
    },
    {
        "row": 390,
        "col": 1486,
        "value": 4.0
    },
    {
        "row": 390,
        "col": 1535,
        "value": 1.0
    },
    {
        "row": 390,
        "col": 1555,
        "value": 1.0
    },
    {
        "row": 390,
        "col": 1569,
        "value": 1.0
    },
    {
        "row": 390,
        "col": 1601,
        "value": 1.0
    },
    {
        "row": 390,
        "col": 1608,
        "value": 7.0
    },
    {
        "row": 390,
        "col": 1620,
        "value": 1.0
    },
    {
        "row": 390,
        "col": 1622,
        "value": 1.0
    },
    {
        "row": 390,
        "col": 1697,
        "value": 1.0
    },
    {
        "row": 390,
        "col": 1703,
        "value": 1.0
    },
    {
        "row": 390,
        "col": 1714,
        "value": 1.0
    },
    {
        "row": 390,
        "col": 1761,
        "value": 2.0
    },
    {
        "row": 390,
        "col": 1783,
        "value": 1.0
    },
    {
        "row": 390,
        "col": 1794,
        "value": 1.0
    },
    {
        "row": 390,
        "col": 1798,
        "value": 2.0
    },
    {
        "row": 390,
        "col": 1817,
        "value": 3.0
    },
    {
        "row": 390,
        "col": 1823,
        "value": 2.0
    },
    {
        "row": 390,
        "col": 1829,
        "value": 1.0
    },
    {
        "row": 390,
        "col": 1866,
        "value": 1.0
    },
    {
        "row": 390,
        "col": 1911,
        "value": 2.0
    },
    {
        "row": 390,
        "col": 1916,
        "value": 1.0
    },
    {
        "row": 390,
        "col": 1932,
        "value": 1.0
    },
    {
        "row": 390,
        "col": 1936,
        "value": 1.0
    },
    {
        "row": 390,
        "col": 1976,
        "value": 1.0
    },
    {
        "row": 390,
        "col": 2008,
        "value": 1.0
    },
    {
        "row": 390,
        "col": 2011,
        "value": 1.0
    },
    {
        "row": 390,
        "col": 2022,
        "value": 1.0
    },
    {
        "row": 390,
        "col": 2026,
        "value": 3.0
    },
    {
        "row": 390,
        "col": 2028,
        "value": 1.0
    },
    {
        "row": 390,
        "col": 2030,
        "value": 1.0
    },
    {
        "row": 390,
        "col": 2045,
        "value": 1.0
    },
    {
        "row": 390,
        "col": 2052,
        "value": 1.0
    },
    {
        "row": 390,
        "col": 2062,
        "value": 1.0
    },
    {
        "row": 390,
        "col": 2066,
        "value": 1.0
    },
    {
        "row": 390,
        "col": 2091,
        "value": 1.0
    },
    {
        "row": 390,
        "col": 2131,
        "value": 1.0
    },
    {
        "row": 390,
        "col": 2158,
        "value": 1.0
    },
    {
        "row": 390,
        "col": 2183,
        "value": 1.0
    },
    {
        "row": 390,
        "col": 2196,
        "value": 2.0
    },
    {
        "row": 390,
        "col": 2210,
        "value": 1.0
    },
    {
        "row": 390,
        "col": 2243,
        "value": 2.0
    },
    {
        "row": 390,
        "col": 2247,
        "value": 1.0
    },
    {
        "row": 390,
        "col": 2262,
        "value": 1.0
    },
    {
        "row": 390,
        "col": 2269,
        "value": 2.0
    },
    {
        "row": 390,
        "col": 2312,
        "value": 2.0
    },
    {
        "row": 390,
        "col": 2314,
        "value": 1.0
    },
    {
        "row": 390,
        "col": 2318,
        "value": 1.0
    },
    {
        "row": 390,
        "col": 2321,
        "value": 1.0
    },
    {
        "row": 390,
        "col": 2350,
        "value": 1.0
    },
    {
        "row": 390,
        "col": 2354,
        "value": 3.0
    },
    {
        "row": 390,
        "col": 2389,
        "value": 1.0
    },
    {
        "row": 390,
        "col": 2412,
        "value": 1.0
    },
    {
        "row": 390,
        "col": 2415,
        "value": 1.0
    },
    {
        "row": 390,
        "col": 2445,
        "value": 1.0
    },
    {
        "row": 390,
        "col": 2446,
        "value": 1.0
    },
    {
        "row": 390,
        "col": 2447,
        "value": 3.0
    },
    {
        "row": 390,
        "col": 2449,
        "value": 1.0
    },
    {
        "row": 390,
        "col": 2488,
        "value": 1.0
    },
    {
        "row": 390,
        "col": 2508,
        "value": 1.0
    },
    {
        "row": 390,
        "col": 2530,
        "value": 1.0
    },
    {
        "row": 390,
        "col": 2554,
        "value": 4.0
    },
    {
        "row": 390,
        "col": 2572,
        "value": 1.0
    },
    {
        "row": 390,
        "col": 2580,
        "value": 1.0
    },
    {
        "row": 390,
        "col": 2619,
        "value": 1.0
    },
    {
        "row": 390,
        "col": 2621,
        "value": 1.0
    },
    {
        "row": 390,
        "col": 2656,
        "value": 1.0
    },
    {
        "row": 390,
        "col": 2665,
        "value": 1.0
    },
    {
        "row": 390,
        "col": 2668,
        "value": 1.0
    },
    {
        "row": 390,
        "col": 2672,
        "value": 1.0
    },
    {
        "row": 390,
        "col": 2688,
        "value": 1.0
    },
    {
        "row": 390,
        "col": 2690,
        "value": 1.0
    },
    {
        "row": 390,
        "col": 2757,
        "value": 1.0
    },
    {
        "row": 390,
        "col": 2766,
        "value": 1.0
    },
    {
        "row": 390,
        "col": 2778,
        "value": 1.0
    },
    {
        "row": 390,
        "col": 2816,
        "value": 3.0
    },
    {
        "row": 390,
        "col": 2820,
        "value": 1.0
    },
    {
        "row": 390,
        "col": 2832,
        "value": 1.0
    },
    {
        "row": 390,
        "col": 2837,
        "value": 1.0
    },
    {
        "row": 390,
        "col": 2851,
        "value": 1.0
    },
    {
        "row": 390,
        "col": 2855,
        "value": 1.0
    },
    {
        "row": 390,
        "col": 2905,
        "value": 1.0
    },
    {
        "row": 390,
        "col": 2922,
        "value": 1.0
    },
    {
        "row": 390,
        "col": 2931,
        "value": 1.0
    },
    {
        "row": 390,
        "col": 2933,
        "value": 1.0
    },
    {
        "row": 390,
        "col": 2953,
        "value": 1.0
    },
    {
        "row": 398,
        "col": 648,
        "value": 1.0
    },
    {
        "row": 413,
        "col": 2269,
        "value": 1.0
    },
    {
        "row": 413,
        "col": 2676,
        "value": 2.0
    },
    {
        "row": 420,
        "col": 970,
        "value": 1.0
    },
    {
        "row": 420,
        "col": 1180,
        "value": 1.0
    },
    {
        "row": 420,
        "col": 1861,
        "value": 1.0
    },
    {
        "row": 420,
        "col": 2667,
        "value": 1.0
    },
    {
        "row": 420,
        "col": 2685,
        "value": 1.0
    },
    {
        "row": 423,
        "col": 2269,
        "value": 1.0
    },
    {
        "row": 423,
        "col": 2676,
        "value": 2.0
    },
    {
        "row": 430,
        "col": 160,
        "value": 2.0
    },
    {
        "row": 430,
        "col": 821,
        "value": 1.0
    },
    {
        "row": 430,
        "col": 1282,
        "value": 1.0
    },
    {
        "row": 430,
        "col": 1697,
        "value": 1.0
    },
    {
        "row": 430,
        "col": 1936,
        "value": 1.0
    },
    {
        "row": 430,
        "col": 2269,
        "value": 2.0
    },
    {
        "row": 430,
        "col": 2389,
        "value": 1.0
    },
    {
        "row": 430,
        "col": 2931,
        "value": 1.0
    },
    {
        "row": 433,
        "col": 163,
        "value": 1.0
    },
    {
        "row": 433,
        "col": 846,
        "value": 2.0
    },
    {
        "row": 433,
        "col": 976,
        "value": 1.0
    },
    {
        "row": 433,
        "col": 1067,
        "value": 1.0
    },
    {
        "row": 433,
        "col": 1316,
        "value": 1.0
    },
    {
        "row": 433,
        "col": 1552,
        "value": 3.0
    },
    {
        "row": 433,
        "col": 1743,
        "value": 2.0
    },
    {
        "row": 433,
        "col": 2423,
        "value": 3.0
    },
    {
        "row": 433,
        "col": 2542,
        "value": 2.0
    },
    {
        "row": 433,
        "col": 2548,
        "value": 2.0
    },
    {
        "row": 433,
        "col": 2671,
        "value": 2.0
    },
    {
        "row": 435,
        "col": 834,
        "value": 1.0
    },
    {
        "row": 435,
        "col": 979,
        "value": 1.0
    },
    {
        "row": 435,
        "col": 997,
        "value": 1.0
    },
    {
        "row": 435,
        "col": 1063,
        "value": 1.0
    },
    {
        "row": 435,
        "col": 1074,
        "value": 1.0
    },
    {
        "row": 435,
        "col": 1466,
        "value": 1.0
    },
    {
        "row": 435,
        "col": 1664,
        "value": 1.0
    },
    {
        "row": 435,
        "col": 1989,
        "value": 1.0
    },
    {
        "row": 435,
        "col": 2896,
        "value": 1.0
    },
    {
        "row": 449,
        "col": 1437,
        "value": 1.0
    },
    {
        "row": 449,
        "col": 1789,
        "value": 1.0
    },
    {
        "row": 458,
        "col": 281,
        "value": 1.0
    },
    {
        "row": 458,
        "col": 1087,
        "value": 1.0
    },
    {
        "row": 458,
        "col": 1263,
        "value": 1.0
    },
    {
        "row": 464,
        "col": 544,
        "value": 1.0
    },
    {
        "row": 464,
        "col": 970,
        "value": 1.0
    },
    {
        "row": 464,
        "col": 2356,
        "value": 1.0
    },
    {
        "row": 464,
        "col": 2409,
        "value": 1.0
    },
    {
        "row": 464,
        "col": 2478,
        "value": 1.0
    },
    {
        "row": 465,
        "col": 300,
        "value": 1.0
    },
    {
        "row": 465,
        "col": 2415,
        "value": 1.0
    },
    {
        "row": 465,
        "col": 2905,
        "value": 1.0
    },
    {
        "row": 466,
        "col": 0,
        "value": 1.0
    },
    {
        "row": 471,
        "col": 100,
        "value": 2.0
    },
    {
        "row": 471,
        "col": 162,
        "value": 1.0
    },
    {
        "row": 471,
        "col": 212,
        "value": 1.0
    },
    {
        "row": 471,
        "col": 478,
        "value": 2.0
    },
    {
        "row": 471,
        "col": 482,
        "value": 1.0
    },
    {
        "row": 471,
        "col": 502,
        "value": 1.0
    },
    {
        "row": 471,
        "col": 552,
        "value": 1.0
    },
    {
        "row": 471,
        "col": 618,
        "value": 1.0
    },
    {
        "row": 471,
        "col": 756,
        "value": 1.0
    },
    {
        "row": 471,
        "col": 783,
        "value": 1.0
    },
    {
        "row": 471,
        "col": 915,
        "value": 1.0
    },
    {
        "row": 471,
        "col": 940,
        "value": 3.0
    },
    {
        "row": 471,
        "col": 970,
        "value": 1.0
    },
    {
        "row": 471,
        "col": 975,
        "value": 2.0
    },
    {
        "row": 471,
        "col": 1011,
        "value": 1.0
    },
    {
        "row": 471,
        "col": 1038,
        "value": 1.0
    },
    {
        "row": 471,
        "col": 1099,
        "value": 1.0
    },
    {
        "row": 471,
        "col": 1378,
        "value": 2.0
    },
    {
        "row": 471,
        "col": 1399,
        "value": 1.0
    },
    {
        "row": 471,
        "col": 1510,
        "value": 1.0
    },
    {
        "row": 471,
        "col": 1778,
        "value": 1.0
    },
    {
        "row": 471,
        "col": 1826,
        "value": 1.0
    },
    {
        "row": 471,
        "col": 2040,
        "value": 2.0
    },
    {
        "row": 471,
        "col": 2075,
        "value": 1.0
    },
    {
        "row": 471,
        "col": 2262,
        "value": 1.0
    },
    {
        "row": 471,
        "col": 2482,
        "value": 3.0
    },
    {
        "row": 471,
        "col": 2539,
        "value": 2.0
    },
    {
        "row": 471,
        "col": 2570,
        "value": 2.0
    },
    {
        "row": 471,
        "col": 2620,
        "value": 1.0
    },
    {
        "row": 471,
        "col": 2782,
        "value": 1.0
    },
    {
        "row": 471,
        "col": 2799,
        "value": 1.0
    },
    {
        "row": 471,
        "col": 2881,
        "value": 1.0
    },
    {
        "row": 471,
        "col": 2892,
        "value": 1.0
    },
    {
        "row": 471,
        "col": 2951,
        "value": 1.0
    },
    {
        "row": 473,
        "col": 26,
        "value": 1.0
    },
    {
        "row": 473,
        "col": 1705,
        "value": 1.0
    },
    {
        "row": 475,
        "col": 253,
        "value": 1.0
    },
    {
        "row": 475,
        "col": 853,
        "value": 1.0
    },
    {
        "row": 475,
        "col": 1465,
        "value": 2.0
    },
    {
        "row": 475,
        "col": 1519,
        "value": 2.0
    },
    {
        "row": 475,
        "col": 2150,
        "value": 2.0
    },
    {
        "row": 475,
        "col": 2646,
        "value": 2.0
    },
    {
        "row": 475,
        "col": 2773,
        "value": 2.0
    },
    {
        "row": 477,
        "col": 0,
        "value": 1.0
    },
    {
        "row": 479,
        "col": 214,
        "value": 1.0
    },
    {
        "row": 479,
        "col": 277,
        "value": 1.0
    },
    {
        "row": 479,
        "col": 1333,
        "value": 1.0
    },
    {
        "row": 481,
        "col": 18,
        "value": 2.0
    },
    {
        "row": 481,
        "col": 586,
        "value": 1.0
    },
    {
        "row": 481,
        "col": 793,
        "value": 2.0
    },
    {
        "row": 481,
        "col": 957,
        "value": 1.0
    },
    {
        "row": 481,
        "col": 1021,
        "value": 1.0
    },
    {
        "row": 481,
        "col": 1100,
        "value": 1.0
    },
    {
        "row": 481,
        "col": 1307,
        "value": 1.0
    },
    {
        "row": 481,
        "col": 1415,
        "value": 1.0
    },
    {
        "row": 481,
        "col": 1622,
        "value": 1.0
    },
    {
        "row": 481,
        "col": 1916,
        "value": 1.0
    },
    {
        "row": 481,
        "col": 1976,
        "value": 1.0
    },
    {
        "row": 481,
        "col": 2052,
        "value": 1.0
    },
    {
        "row": 481,
        "col": 2158,
        "value": 1.0
    },
    {
        "row": 481,
        "col": 2196,
        "value": 1.0
    },
    {
        "row": 481,
        "col": 2354,
        "value": 2.0
    },
    {
        "row": 481,
        "col": 2412,
        "value": 1.0
    },
    {
        "row": 481,
        "col": 2665,
        "value": 1.0
    },
    {
        "row": 481,
        "col": 2668,
        "value": 1.0
    },
    {
        "row": 481,
        "col": 2688,
        "value": 1.0
    },
    {
        "row": 481,
        "col": 2816,
        "value": 2.0
    },
    {
        "row": 481,
        "col": 2953,
        "value": 1.0
    },
    {
        "row": 485,
        "col": 416,
        "value": 1.0
    },
    {
        "row": 485,
        "col": 1604,
        "value": 1.0
    },
    {
        "row": 485,
        "col": 1696,
        "value": 1.0
    },
    {
        "row": 485,
        "col": 2945,
        "value": 1.0
    },
    {
        "row": 487,
        "col": 378,
        "value": 1.0
    },
    {
        "row": 487,
        "col": 600,
        "value": 1.0
    },
    {
        "row": 487,
        "col": 1094,
        "value": 1.0
    },
    {
        "row": 487,
        "col": 1242,
        "value": 2.0
    },
    {
        "row": 489,
        "col": 214,
        "value": 1.0
    },
    {
        "row": 489,
        "col": 277,
        "value": 1.0
    },
    {
        "row": 489,
        "col": 1333,
        "value": 1.0
    },
    {
        "row": 489,
        "col": 1437,
        "value": 1.0
    },
    {
        "row": 489,
        "col": 1557,
        "value": 1.0
    },
    {
        "row": 489,
        "col": 1789,
        "value": 1.0
    },
    {
        "row": 489,
        "col": 2171,
        "value": 1.0
    },
    {
        "row": 489,
        "col": 2269,
        "value": 1.0
    },
    {
        "row": 489,
        "col": 2676,
        "value": 2.0
    },
    {
        "row": 490,
        "col": 0,
        "value": 1.0
    },
    {
        "row": 497,
        "col": 497,
        "value": 1.0
    },
    {
        "row": 497,
        "col": 867,
        "value": 1.0
    },
    {
        "row": 497,
        "col": 924,
        "value": 1.0
    },
    {
        "row": 497,
        "col": 1054,
        "value": 1.0
    },
    {
        "row": 497,
        "col": 1188,
        "value": 1.0
    },
    {
        "row": 497,
        "col": 1280,
        "value": 1.0
    },
    {
        "row": 497,
        "col": 2015,
        "value": 1.0
    },
    {
        "row": 497,
        "col": 2489,
        "value": 1.0
    },
    {
        "row": 502,
        "col": 1135,
        "value": 1.0
    },
    {
        "row": 507,
        "col": 636,
        "value": 1.0
    },
    {
        "row": 507,
        "col": 738,
        "value": 1.0
    },
    {
        "row": 508,
        "col": 131,
        "value": 1.0
    },
    {
        "row": 508,
        "col": 640,
        "value": 1.0
    },
    {
        "row": 508,
        "col": 1410,
        "value": 1.0
    },
    {
        "row": 508,
        "col": 2262,
        "value": 1.0
    },
    {
        "row": 508,
        "col": 2416,
        "value": 1.0
    },
    {
        "row": 508,
        "col": 2497,
        "value": 1.0
    },
    {
        "row": 508,
        "col": 2530,
        "value": 1.0
    },
    {
        "row": 511,
        "col": 83,
        "value": 1.0
    },
    {
        "row": 511,
        "col": 816,
        "value": 1.0
    },
    {
        "row": 511,
        "col": 970,
        "value": 1.0
    },
    {
        "row": 511,
        "col": 1079,
        "value": 1.0
    },
    {
        "row": 511,
        "col": 1180,
        "value": 1.0
    },
    {
        "row": 516,
        "col": 75,
        "value": 2.0
    },
    {
        "row": 516,
        "col": 99,
        "value": 1.0
    },
    {
        "row": 516,
        "col": 233,
        "value": 1.0
    },
    {
        "row": 516,
        "col": 290,
        "value": 1.0
    },
    {
        "row": 516,
        "col": 299,
        "value": 1.0
    },
    {
        "row": 516,
        "col": 331,
        "value": 1.0
    },
    {
        "row": 516,
        "col": 463,
        "value": 3.0
    },
    {
        "row": 516,
        "col": 509,
        "value": 1.0
    },
    {
        "row": 516,
        "col": 551,
        "value": 1.0
    },
    {
        "row": 516,
        "col": 575,
        "value": 1.0
    },
    {
        "row": 516,
        "col": 636,
        "value": 1.0
    },
    {
        "row": 516,
        "col": 738,
        "value": 1.0
    },
    {
        "row": 516,
        "col": 882,
        "value": 1.0
    },
    {
        "row": 516,
        "col": 938,
        "value": 1.0
    },
    {
        "row": 516,
        "col": 970,
        "value": 4.0
    },
    {
        "row": 516,
        "col": 1011,
        "value": 1.0
    },
    {
        "row": 516,
        "col": 1079,
        "value": 1.0
    },
    {
        "row": 516,
        "col": 1111,
        "value": 1.0
    },
    {
        "row": 516,
        "col": 1180,
        "value": 2.0
    },
    {
        "row": 516,
        "col": 1196,
        "value": 1.0
    },
    {
        "row": 516,
        "col": 1277,
        "value": 1.0
    },
    {
        "row": 516,
        "col": 1350,
        "value": 1.0
    },
    {
        "row": 516,
        "col": 1486,
        "value": 2.0
    },
    {
        "row": 516,
        "col": 1608,
        "value": 1.0
    },
    {
        "row": 516,
        "col": 1733,
        "value": 1.0
    },
    {
        "row": 516,
        "col": 1787,
        "value": 1.0
    },
    {
        "row": 516,
        "col": 1807,
        "value": 1.0
    },
    {
        "row": 516,
        "col": 1861,
        "value": 1.0
    },
    {
        "row": 516,
        "col": 1991,
        "value": 1.0
    },
    {
        "row": 516,
        "col": 2062,
        "value": 3.0
    },
    {
        "row": 516,
        "col": 2068,
        "value": 1.0
    },
    {
        "row": 516,
        "col": 2105,
        "value": 1.0
    },
    {
        "row": 516,
        "col": 2135,
        "value": 1.0
    },
    {
        "row": 516,
        "col": 2141,
        "value": 2.0
    },
    {
        "row": 516,
        "col": 2262,
        "value": 3.0
    },
    {
        "row": 516,
        "col": 2427,
        "value": 1.0
    },
    {
        "row": 516,
        "col": 2504,
        "value": 1.0
    },
    {
        "row": 516,
        "col": 2667,
        "value": 1.0
    },
    {
        "row": 516,
        "col": 2685,
        "value": 1.0
    },
    {
        "row": 516,
        "col": 2730,
        "value": 1.0
    },
    {
        "row": 516,
        "col": 2732,
        "value": 1.0
    },
    {
        "row": 516,
        "col": 2758,
        "value": 1.0
    },
    {
        "row": 517,
        "col": 1557,
        "value": 1.0
    },
    {
        "row": 518,
        "col": 0,
        "value": 1.0
    },
    {
        "row": 519,
        "col": 2171,
        "value": 1.0
    },
    {
        "row": 521,
        "col": 932,
        "value": 1.0
    },
    {
        "row": 521,
        "col": 1188,
        "value": 1.0
    },
    {
        "row": 521,
        "col": 2514,
        "value": 1.0
    },
    {
        "row": 526,
        "col": 42,
        "value": 1.0
    },
    {
        "row": 526,
        "col": 54,
        "value": 1.0
    },
    {
        "row": 526,
        "col": 83,
        "value": 2.0
    },
    {
        "row": 526,
        "col": 120,
        "value": 1.0
    },
    {
        "row": 526,
        "col": 145,
        "value": 1.0
    },
    {
        "row": 526,
        "col": 152,
        "value": 1.0
    },
    {
        "row": 526,
        "col": 157,
        "value": 1.0
    },
    {
        "row": 526,
        "col": 162,
        "value": 1.0
    },
    {
        "row": 526,
        "col": 200,
        "value": 1.0
    },
    {
        "row": 526,
        "col": 233,
        "value": 1.0
    },
    {
        "row": 526,
        "col": 253,
        "value": 1.0
    },
    {
        "row": 526,
        "col": 276,
        "value": 1.0
    },
    {
        "row": 526,
        "col": 279,
        "value": 1.0
    },
    {
        "row": 526,
        "col": 295,
        "value": 1.0
    },
    {
        "row": 526,
        "col": 303,
        "value": 1.0
    },
    {
        "row": 526,
        "col": 326,
        "value": 1.0
    },
    {
        "row": 526,
        "col": 331,
        "value": 1.0
    },
    {
        "row": 526,
        "col": 338,
        "value": 1.0
    },
    {
        "row": 526,
        "col": 360,
        "value": 1.0
    },
    {
        "row": 526,
        "col": 389,
        "value": 1.0
    },
    {
        "row": 526,
        "col": 399,
        "value": 1.0
    },
    {
        "row": 526,
        "col": 463,
        "value": 1.0
    },
    {
        "row": 526,
        "col": 502,
        "value": 1.0
    },
    {
        "row": 526,
        "col": 523,
        "value": 1.0
    },
    {
        "row": 526,
        "col": 601,
        "value": 1.0
    },
    {
        "row": 526,
        "col": 662,
        "value": 1.0
    },
    {
        "row": 526,
        "col": 679,
        "value": 1.0
    },
    {
        "row": 526,
        "col": 737,
        "value": 1.0
    },
    {
        "row": 526,
        "col": 816,
        "value": 2.0
    },
    {
        "row": 526,
        "col": 833,
        "value": 1.0
    },
    {
        "row": 526,
        "col": 834,
        "value": 1.0
    },
    {
        "row": 526,
        "col": 853,
        "value": 1.0
    },
    {
        "row": 526,
        "col": 925,
        "value": 1.0
    },
    {
        "row": 526,
        "col": 954,
        "value": 1.0
    },
    {
        "row": 526,
        "col": 970,
        "value": 10.0
    },
    {
        "row": 526,
        "col": 979,
        "value": 1.0
    },
    {
        "row": 526,
        "col": 980,
        "value": 1.0
    },
    {
        "row": 526,
        "col": 997,
        "value": 1.0
    },
    {
        "row": 526,
        "col": 1000,
        "value": 1.0
    },
    {
        "row": 526,
        "col": 1011,
        "value": 1.0
    },
    {
        "row": 526,
        "col": 1025,
        "value": 1.0
    },
    {
        "row": 526,
        "col": 1035,
        "value": 1.0
    },
    {
        "row": 526,
        "col": 1038,
        "value": 3.0
    },
    {
        "row": 526,
        "col": 1063,
        "value": 1.0
    },
    {
        "row": 526,
        "col": 1072,
        "value": 1.0
    },
    {
        "row": 526,
        "col": 1074,
        "value": 1.0
    },
    {
        "row": 526,
        "col": 1076,
        "value": 5.0
    },
    {
        "row": 526,
        "col": 1079,
        "value": 1.0
    },
    {
        "row": 526,
        "col": 1087,
        "value": 1.0
    },
    {
        "row": 526,
        "col": 1103,
        "value": 1.0
    },
    {
        "row": 526,
        "col": 1167,
        "value": 1.0
    },
    {
        "row": 526,
        "col": 1180,
        "value": 1.0
    },
    {
        "row": 526,
        "col": 1188,
        "value": 2.0
    },
    {
        "row": 526,
        "col": 1211,
        "value": 1.0
    },
    {
        "row": 526,
        "col": 1262,
        "value": 1.0
    },
    {
        "row": 526,
        "col": 1263,
        "value": 4.0
    },
    {
        "row": 526,
        "col": 1351,
        "value": 1.0
    },
    {
        "row": 526,
        "col": 1382,
        "value": 1.0
    },
    {
        "row": 526,
        "col": 1385,
        "value": 1.0
    },
    {
        "row": 526,
        "col": 1465,
        "value": 2.0
    },
    {
        "row": 526,
        "col": 1466,
        "value": 1.0
    },
    {
        "row": 526,
        "col": 1470,
        "value": 1.0
    },
    {
        "row": 526,
        "col": 1519,
        "value": 2.0
    },
    {
        "row": 526,
        "col": 1618,
        "value": 1.0
    },
    {
        "row": 526,
        "col": 1638,
        "value": 1.0
    },
    {
        "row": 526,
        "col": 1640,
        "value": 1.0
    },
    {
        "row": 526,
        "col": 1649,
        "value": 1.0
    },
    {
        "row": 526,
        "col": 1664,
        "value": 1.0
    },
    {
        "row": 526,
        "col": 1739,
        "value": 1.0
    },
    {
        "row": 526,
        "col": 1761,
        "value": 2.0
    },
    {
        "row": 526,
        "col": 1798,
        "value": 1.0
    },
    {
        "row": 526,
        "col": 1817,
        "value": 4.0
    },
    {
        "row": 526,
        "col": 1875,
        "value": 1.0
    },
    {
        "row": 526,
        "col": 1897,
        "value": 1.0
    },
    {
        "row": 526,
        "col": 1964,
        "value": 1.0
    },
    {
        "row": 526,
        "col": 1989,
        "value": 1.0
    },
    {
        "row": 526,
        "col": 1998,
        "value": 1.0
    },
    {
        "row": 526,
        "col": 2001,
        "value": 1.0
    },
    {
        "row": 526,
        "col": 2003,
        "value": 1.0
    },
    {
        "row": 526,
        "col": 2009,
        "value": 1.0
    },
    {
        "row": 526,
        "col": 2051,
        "value": 1.0
    },
    {
        "row": 526,
        "col": 2052,
        "value": 1.0
    },
    {
        "row": 526,
        "col": 2115,
        "value": 1.0
    },
    {
        "row": 526,
        "col": 2118,
        "value": 1.0
    },
    {
        "row": 526,
        "col": 2138,
        "value": 1.0
    },
    {
        "row": 526,
        "col": 2141,
        "value": 1.0
    },
    {
        "row": 526,
        "col": 2150,
        "value": 2.0
    },
    {
        "row": 526,
        "col": 2194,
        "value": 1.0
    },
    {
        "row": 526,
        "col": 2210,
        "value": 1.0
    },
    {
        "row": 526,
        "col": 2243,
        "value": 4.0
    },
    {
        "row": 526,
        "col": 2270,
        "value": 1.0
    },
    {
        "row": 526,
        "col": 2470,
        "value": 1.0
    },
    {
        "row": 526,
        "col": 2508,
        "value": 1.0
    },
    {
        "row": 526,
        "col": 2525,
        "value": 1.0
    },
    {
        "row": 526,
        "col": 2554,
        "value": 2.0
    },
    {
        "row": 526,
        "col": 2569,
        "value": 1.0
    },
    {
        "row": 526,
        "col": 2642,
        "value": 1.0
    },
    {
        "row": 526,
        "col": 2646,
        "value": 2.0
    },
    {
        "row": 526,
        "col": 2657,
        "value": 1.0
    },
    {
        "row": 526,
        "col": 2663,
        "value": 1.0
    },
    {
        "row": 526,
        "col": 2685,
        "value": 1.0
    },
    {
        "row": 526,
        "col": 2730,
        "value": 1.0
    },
    {
        "row": 526,
        "col": 2741,
        "value": 1.0
    },
    {
        "row": 526,
        "col": 2757,
        "value": 1.0
    },
    {
        "row": 526,
        "col": 2763,
        "value": 1.0
    },
    {
        "row": 526,
        "col": 2773,
        "value": 2.0
    },
    {
        "row": 526,
        "col": 2793,
        "value": 1.0
    },
    {
        "row": 526,
        "col": 2794,
        "value": 1.0
    },
    {
        "row": 526,
        "col": 2798,
        "value": 1.0
    },
    {
        "row": 526,
        "col": 2801,
        "value": 1.0
    },
    {
        "row": 526,
        "col": 2814,
        "value": 1.0
    },
    {
        "row": 526,
        "col": 2817,
        "value": 1.0
    },
    {
        "row": 526,
        "col": 2839,
        "value": 1.0
    },
    {
        "row": 526,
        "col": 2857,
        "value": 1.0
    },
    {
        "row": 526,
        "col": 2891,
        "value": 1.0
    },
    {
        "row": 526,
        "col": 2892,
        "value": 1.0
    },
    {
        "row": 526,
        "col": 2896,
        "value": 1.0
    },
    {
        "row": 526,
        "col": 2943,
        "value": 1.0
    },
    {
        "row": 537,
        "col": 609,
        "value": 1.0
    },
    {
        "row": 537,
        "col": 1385,
        "value": 1.0
    },
    {
        "row": 543,
        "col": 37,
        "value": 1.0
    },
    {
        "row": 543,
        "col": 453,
        "value": 1.0
    },
    {
        "row": 543,
        "col": 1127,
        "value": 2.0
    },
    {
        "row": 543,
        "col": 1845,
        "value": 1.0
    },
    {
        "row": 543,
        "col": 2139,
        "value": 2.0
    },
    {
        "row": 543,
        "col": 2529,
        "value": 1.0
    },
    {
        "row": 556,
        "col": 50,
        "value": 1.0
    },
    {
        "row": 556,
        "col": 84,
        "value": 1.0
    },
    {
        "row": 556,
        "col": 1173,
        "value": 1.0
    },
    {
        "row": 556,
        "col": 1228,
        "value": 1.0
    },
    {
        "row": 556,
        "col": 1435,
        "value": 1.0
    },
    {
        "row": 556,
        "col": 1552,
        "value": 1.0
    },
    {
        "row": 556,
        "col": 1603,
        "value": 1.0
    },
    {
        "row": 556,
        "col": 1823,
        "value": 1.0
    },
    {
        "row": 556,
        "col": 1890,
        "value": 1.0
    },
    {
        "row": 556,
        "col": 2068,
        "value": 1.0
    },
    {
        "row": 556,
        "col": 2385,
        "value": 1.0
    },
    {
        "row": 556,
        "col": 2423,
        "value": 1.0
    },
    {
        "row": 556,
        "col": 2457,
        "value": 1.0
    },
    {
        "row": 556,
        "col": 2544,
        "value": 2.0
    },
    {
        "row": 559,
        "col": 1342,
        "value": 1.0
    },
    {
        "row": 559,
        "col": 1351,
        "value": 1.0
    },
    {
        "row": 559,
        "col": 1949,
        "value": 1.0
    },
    {
        "row": 559,
        "col": 2054,
        "value": 1.0
    },
    {
        "row": 559,
        "col": 2455,
        "value": 1.0
    },
    {
        "row": 592,
        "col": 2544,
        "value": 1.0
    }
]